magicoca-1.0.9.dist-info/METADATA
magicoca-1.0.9.dist-info/WHEEL
magicoca-1.0.9.dist-info/entry_points.txt
magicoca-1.0.9.dist-info/licenses/LICENSE
magicoca/__init__.py
magicoca/chan.py
magicoca/py.typed
magicoca-1.0.9.dist-info/RECORD
