Metadata-Version: 2.1
Name: magicoca
Version: 1.0.9
Summary: A communication library for Python
Author-Email: snowykami <snowykami@outlook.com>
License: MIT
Requires-Python: >=3.10
